{"card_type": 9, "profile_type_id": "proweibo_5108312213294548", "itemid": "1076037478855230_-_5108312213294548", "scheme": "https://m.weibo.cn/status/P3ueNdP3S?mblogid=P3ueNdP3S", "mblog": {"visible": {"type": 0, "list_id": 0}, "created_at": "Thu Dec 05 20:00:02 +0800 2024", "id": "5108312213294548", "mid": "5108312213294548", "can_edit": false, "text": "<a  href=\"https://m.weibo.cn/p/index?extparam=%E5%91%A8%E6%B7%B1&containerid=100808cbec86fbcc1c453633f835c10c9db0ee\" data-hide=\"\"><span class='url-icon'><img style='width: 1rem;height: 1rem' src='https://n.sinaimg.cn/photo/5213b46e/20180926/timeline_card_small_super_default.png'></span><span class=\"surl-text\">\u5468\u6df1</span></a>\ud83c\udfb5 <a  href=\"https://m.weibo.cn/search?containerid=231522type%3D1%26t%3D10%26q%3D%232024%E5%91%A8%E6%B7%B19.29Hz%E5%B7%A1%E5%9B%9E%E6%BC%94%E5%94%B1%E4%BC%9A%23&extparam=%232024%E5%91%A8%E6%B7%B19.29Hz%E5%B7%A1%E5%9B%9E%E6%BC%94%E5%94%B1%E4%BC%9A%23\" data-hide=\"\"><span class=\"surl-text\">#2024\u5468\u6df19.29Hz\u5de1\u56de\u6f14\u5531\u4f1a#</span></a><br />\u548c\u300a\u53cd\u6df1\u4ee3\u8bcd\u300b\u89c1\u9762\u7684\u7b2c250\u5929\uff0c<br />\u57289.29Hz\u91cc\u5171\u632f\u7684\u7b2c202\u5929\uff0c<br />\u6bcf\u4e00\u6b21\u521d\u89c1\u9762\uff0c\u90fd\u662f\u7d27\u5f20\u800c\u53c8\u6fc0\u52a8\u7684\u3002<br />\u6b4c\u58f0\u98d8\u8fc7\u7684\u5730\u65b9\u90fd\u7559\u4e0b\u4e86\u6211\u4eec\u5171\u540c\u56de\u5fc6\uff0c<br />\u5e0c\u671b\u603b\u6709\u4e00\u9996\u6b4c\u7684\u821e\u53f0\u80fd\u6070\u5408\u4f60\u7684\u5fc3\u610f\u3002<br />\u4f60\u8fd8\u671f\u5f85\u54ea\u4e00\u9996\u6b4c\u7684\u821e\u53f0\uff1f<br /><a  href=\"https://m.weibo.cn/search?containerid=231522type%3D1%26t%3D10%26q%3D%23%E5%91%A8%E6%B7%B1%E5%8D%97%E5%AE%81%E6%BC%94%E5%94%B1%E4%BC%9A%23&extparam=%23%E5%91%A8%E6%B7%B1%E5%8D%97%E5%AE%81%E6%BC%94%E5%94%B1%E4%BC%9A%23\" data-hide=\"\"><span class=\"surl-text\">#\u5468\u6df1\u5357\u5b81\u6f14\u5531\u4f1a#</span></a> \u5012\u8ba1\u65f6\u4e00\u5929\uff0c\u548c\u5468\u6df1 ...<a href=\"/status/5108312213294548\">\u5168\u6587</a>", "textLength": 323, "source": "\u5fae\u535a\u89c6\u9891\u53f7", "favorited": false, "pic_ids": [], "is_paid": false, "mblog_vip_type": 0, "user": {"id": 7478855230, "screen_name": "\u5468\u6df1\u5de5\u4f5c\u5ba4", "profile_image_url": "https://tvax3.sinaimg.cn/crop.0.0.512.512.180/008a8vTgly8heihrtkqqjj30e80e83yq.jpg?KID=imgbed,tva&Expires=1733410807&ssig=B3ezKoQgic", "profile_url": "https://m.weibo.cn/u/7478855230?", "close_blue_v": false, "description": "\u5de5\u4f5c\u4e8b\u5b9c\u8bf7\u8054\u7cfbAlan\uff0c\u90ae\u7bb1\uff1aalan@zhoushenstudio.com", "follow_me": false, "following": false, "follow_count": 15, "followers_count": "101.3\u4e07", "cover_image_phone": "https://tva1.sinaimg.cn/crop.0.0.640.640.640/549d0121tw1egm1kjly3jj20hs0hsq4f.jpg", "avatar_hd": "https://wx3.sinaimg.cn/orj480/008a8vTgly8heihrtkqqjj30e80e83yq.jpg", "badge": {"user_name_certificate": 1, "pc_new": 7, "party_cardid_state": 2, "aoyun_2021": 1, "hongbaofei2022_2021": 2, "iplocationchange_2022": 1, "biyeji_2022": 1, "city_university": 4, "gaokao_2022": 1, "hangmu_2022": 1, "guoqi_2022": 1, "gangqi_2022": 1, "guoq_2022": 1, "ranghongbaofei_2023": 1, "yayunhuiguoqi_2023": 1, "nihaochuntian_2024": 1, "gaokao_2024": 1}, "statuses_count": 1800, "verified": true, "verified_type": 7, "gender": "m", "mbtype": 12, "svip": 1, "urank": 0, "mbrank": 1, "followers_count_str": "101.3\u4e07", "verified_type_ext": 50, "verified_reason": "\u5468\u6df1\u5de5\u4f5c\u5ba4\u5b98\u65b9\u5fae\u535a", "like": false, "like_me": false, "special_follow": false}, "reposts_count": 0, "comments_count": 0, "reprint_cmt_count": 0, "attitudes_count": 0, "mixed_count": 0, "pending_approval_count": 0, "isLongText": true, "show_mlevel": 0, "darwin_tags": [], "ad_marked": false, "mblogtype": 0, "item_category": "status", "rid": "0_0_50_165196511063096405_0_0_0", "cardid": "star_1605", "extern_safe": 0, "number_display_strategy": {"apply_scenario_flag": 19, "display_text_min_number": 1000000, "display_text": "100\u4e07+"}, "content_auth": 0, "is_show_mixed": false, "comment_manage_info": {"comment_permission_type": -1, "approval_comment_type": 0, "comment_sort_type": 0}, "pic_num": 0, "fid": 5108293302222885, "mlevel": 0, "region_name": "\u53d1\u5e03\u4e8e \u5e7f\u897f", "region_opt": 1, "detail_bottom_bar": 0, "analysis_extra": "follow:0", "mblog_menu_new_style": 0, "edit_config": {"edited": false}, "page_info": {"type": "video", "object_type": 11, "url_ori": "http://t.cn/A6mSDqXT", "page_pic": {"width": "1920", "pid": "008a8vTggy1hwa8i5pojdj31hc0u0h01", "source": "2", "is_self_cover": "1", "type": "1", "url": "https://wx2.sinaimg.cn/orj480/008a8vTggy1hwa8i5pojdj31hc0u0h01.jpg", "height": "1080"}, "page_url": "https://video.weibo.com/show?fid=1034%3A5108293140676662", "object_id": "1034:5108293140676662", "page_title": "\u5468\u6df1\u5de5\u4f5c\u5ba4\u7684\u5fae\u535a\u89c6\u9891", "title": "2024 \u5468\u6df1 9.29Hz\u5de1\u56de\u6f14\u5531\u4f1a \u5357\u5b81\u7ad9\u5012\u8ba1\u65f6", "content1": "\u5468\u6df1\u5de5\u4f5c\u5ba4\u7684\u5fae\u535a\u89c6\u9891", "content2": "#\u5468\u6df1[\u8d85\u8bdd]#\ud83c\udfb5 #2024\u5468\u6df19.29Hz\u5de1\u56de\u6f14\u5531\u4f1a#\n\u548c\u300a\u53cd\u6df1\u4ee3\u8bcd\u300b\u89c1\u9762\u7684\u7b2c250\u5929\uff0c\n\u57289.29Hz\u91cc\u5171\u632f\u7684\u7b2c202\u5929\uff0c\n\u6bcf\u4e00\u6b21\u521d\u89c1\u9762\uff0c\u90fd\u662f\u7d27\u5f20\u800c\u53c8\u6fc0\u52a8\u7684\u3002\n\u6b4c\u58f0\u98d8\u8fc7\u7684\u5730\u65b9\u90fd\u7559\u4e0b\u4e86\u6211\u4eec\u5171\u540c\u56de\u5fc6\uff0c\n\u5e0c\u671b\u603b\u6709\u4e00\u9996\u6b4c\u7684\u821e\u53f0\u80fd\u6070\u5408\u4f60\u7684\u5fc3\u610f\u3002\n\u4f60\u8fd8\u671f\u5f85\u54ea\u4e00\u9996\u6b4c\u7684\u821e\u53f0\uff1f\n#\u5468\u6df1\u5357\u5b81", "video_orientation": "horizontal", "play_count": "15\u6b21\u64ad\u653e", "media_info": {"stream_url": "https://f.video.weibocdn.com/u0/rIdDMvrpgx08k7Ow8Mda01041201cMhP0E010.mp4?label=mp4_ld&template=640x360.25.0&ori=0&ps=1CvO5Ia5FwDueA&Expires=1733403605&ssig=nFtrNNJoHo&KID=unistore,video", "stream_url_hd": "https://f.video.weibocdn.com/u0/5qahtz9agx08k7OvYx9K01041201Y87e0E010.mp4?label=mp4_hd&template=852x480.25.0&ori=0&ps=1CvO5Ia5FwDueA&Expires=1733403605&ssig=FTOLqYtuU7&KID=unistore,video", "duration": 265.101}, "urls": {"mp4_720p_mp4": "https://f.video.weibocdn.com/u0/K5wpulcmgx08k7OxBays01041203MVKT0E020.mp4?label=mp4_720p&template=1280x720.25.0&ori=0&ps=1CvO5Ia5FwDueA&Expires=1733403605&ssig=6RkBU5kxZS&KID=unistore,video", "mp4_hd_mp4": "https://f.video.weibocdn.com/u0/5qahtz9agx08k7OvYx9K01041201Y87e0E010.mp4?label=mp4_hd&template=852x480.25.0&ori=0&ps=1CvO5Ia5FwDueA&Expires=1733403605&ssig=FTOLqYtuU7&KID=unistore,video", "mp4_ld_mp4": "https://f.video.weibocdn.com/u0/rIdDMvrpgx08k7Ow8Mda01041201cMhP0E010.mp4?label=mp4_ld&template=640x360.25.0&ori=0&ps=1CvO5Ia5FwDueA&Expires=1733403605&ssig=nFtrNNJoHo&KID=unistore,video"}}, "bid": "P3ueNdP3S"}}